pypdf/__init__.py
pypdf/logger.py
pypdf/utils.py
pypdf/bin/__init__.py
pypdf_lib-0.0.3.dist-info/LICENSE
pypdf_lib-0.0.3.dist-info/METADATA
pypdf_lib-0.0.3.dist-info/WHEEL
pypdf_lib-0.0.3.dist-info/top_level.txt
pypdf_lib-0.0.3.dist-info/RECORD
