Metadata-Version: 2.1
Name: pypdf-lib
Version: 0.0.3
Summary: pypdf
Home-page: http://github.com/trisongz/pypdf-lib
Author: Tri Songz
Author-email: ts@growthengineai.com
License: UNKNOWN
Platform: UNKNOWN
Classifier: Development Status :: 3 - Alpha
Classifier: Environment :: Console
Classifier: Intended Audience :: Developers
Requires-Python: >=3.6
Requires-Dist: file-io
